topsis_shubhaan_102203456/__init__.py
topsis_shubhaan_102203456/topsis.py
topsis_shubhaan_102203456-1.2.0.dist-info/LICENSE
topsis_shubhaan_102203456-1.2.0.dist-info/METADATA
topsis_shubhaan_102203456-1.2.0.dist-info/WHEEL
topsis_shubhaan_102203456-1.2.0.dist-info/entry_points.txt
topsis_shubhaan_102203456-1.2.0.dist-info/top_level.txt
topsis_shubhaan_102203456-1.2.0.dist-info/RECORD
