Metadata-Version: 2.1
Name: topsis-shubhaan-102203456
Version: 1.2.0
Summary: A Python package for the TOPSIS method
Home-page: https://github.com/shubhaan06/topsis
Author: Shubhaan Bhandari
Author-email: shubhaan2004@gmail.com
License-File: LICENSE
Requires-Dist: numpy >=1.19.5
Requires-Dist: pandas >=1.1.5
